autodiff/__init__.py
autodiff/autodiff.py
autodiff/tests/__init__.py
autodiff/tests/integration_test.py
autodiff/tests/numpy_test.py
autodiff/tests/test_binary_functions.py
autodiff/tests/test_corner_cases.py
autodiff/tests/test_equalities.py
autodiff/tests/test_unary_functions.py
autodiff/tests/write_unary.py
tests/__init__.py
tests/integration_test.py
tests/numpy_test.py
tests/test_binary_functions.py
tests/test_corner_cases.py
tests/test_equalities.py
tests/test_unary_functions.py
tests/write_unary.py
AutoDiff_group3-0.0.6.dist-info/LICENSE
AutoDiff_group3-0.0.6.dist-info/METADATA
AutoDiff_group3-0.0.6.dist-info/WHEEL
AutoDiff_group3-0.0.6.dist-info/top_level.txt
AutoDiff_group3-0.0.6.dist-info/RECORD
