Metadata-Version: 2.1
Name: AutoDiff-group3
Version: 0.0.6
Summary: Automatic differentiation with dual numbers
Home-page: https://github.com/cs207-project-erin-bruce-will/cs207-FinalProject
Author: Will Claybaugh, Fan (Bruce) Xiong, Erin Williams
Author-email: erinwilliams@g.harvard.edu
License: UNKNOWN
Platform: UNKNOWN
Classifier: Programming Language :: Python :: 3
Classifier: License :: OSI Approved :: MIT License
Classifier: Operating System :: OS Independent
Requires-Dist: numpy
Requires-Dist: pytest
